injectool/__init__.py
injectool/core.py
injectool/injection.py
injectool/resolvers.py
injectool-3.0.0.dist-info/LICENSE
injectool-3.0.0.dist-info/METADATA
injectool-3.0.0.dist-info/WHEEL
injectool-3.0.0.dist-info/top_level.txt
injectool-3.0.0.dist-info/RECORD
