Metadata-Version: 2.1
Name: injectool
Version: 3.0.0
Summary: Dependency injection tool
Project-URL: Homepage, https://github.com/eumis/injectool
Keywords: di,dependency,injection,ioc,inversion of control,inject
Classifier: Development Status :: 5 - Production/Stable
Classifier: Intended Audience :: Developers
Classifier: Topic :: Software Development :: Libraries
Classifier: License :: OSI Approved :: MIT License
Classifier: Programming Language :: Python :: 3.6
Classifier: Operating System :: OS Independent
Requires-Python: >=3.6
License-File: LICENSE
